argo/events/__init__.py
argo/events/client/__about__.py
argo/events/client/__init__.py
argo/events/client/api_client.py
argo/events/client/configuration.py
argo/events/client/exceptions.py
argo/events/client/rest.py
argo/events/client/api/__init__.py
argo/events/client/models/__init__.py
argo/events/client/models/common_backoff.py
argo/events/client/models/common_condition.py
argo/events/client/models/common_metadata.py
argo/events/client/models/common_s3_artifact.py
argo/events/client/models/common_s3_bucket.py
argo/events/client/models/common_s3_filter.py
argo/events/client/models/common_status.py
argo/events/client/models/common_tls_config.py
argo/events/client/models/eventsource_v1alpha1_template.py
argo/events/client/models/sensor_v1alpha1_template.py
argo/events/client/models/v1_affinity.py
argo/events/client/models/v1_affinity_node_affinity.py
argo/events/client/models/v1_affinity_node_affinity_preference.py
argo/events/client/models/v1_affinity_node_affinity_preference_match_expressions.py
argo/events/client/models/v1_affinity_node_affinity_preferred_during_scheduling_ignored_during_execution.py
argo/events/client/models/v1_affinity_node_affinity_required_during_scheduling_ignored_during_execution.py
argo/events/client/models/v1_affinity_pod_affinity.py
argo/events/client/models/v1_affinity_pod_affinity_pod_affinity_term.py
argo/events/client/models/v1_affinity_pod_affinity_pod_affinity_term_label_selector.py
argo/events/client/models/v1_affinity_pod_affinity_pod_affinity_term_label_selector_match_expressions.py
argo/events/client/models/v1_affinity_pod_affinity_preferred_during_scheduling_ignored_during_execution.py
argo/events/client/models/v1_affinity_pod_anti_affinity.py
argo/events/client/models/v1_config_map_key_selector.py
argo/events/client/models/v1_container.py
argo/events/client/models/v1_container_config_map_ref.py
argo/events/client/models/v1_container_env.py
argo/events/client/models/v1_container_env_from.py
argo_events-0.1.0.dist-info/METADATA
argo_events-0.1.0.dist-info/WHEEL
argo_events-0.1.0.dist-info/top_level.txt
argo_events-0.1.0.dist-info/RECORD
